{"ResultObject":[{"Text":"доставить воздушные шары","SuggestionId":14226,"SuggestionType":1,"Location":null,"SubcategoryId":1,"Highlight":[{"Begin":20,"End":22}]},{"Text":"создание шапки для сайта","SuggestionId":13130,"SuggestionType":1,"Location":null,"SubcategoryId":61,"Highlight":[{"Begin":9,"End":11}]},{"Text":"купить и доставить шампанское","SuggestionId":979,"SuggestionType":1,"Location":null,"SubcategoryId":124,"Highlight":[{"Begin":19,"End":21}]},{"Text":"изготовление шаблонов для сайта","SuggestionId":12596,"SuggestionType":1,"Location":null,"SubcategoryId":147,"Highlight":[{"Begin":13,"End":15}]},{"Text":"окрашивание шатуш","SuggestionId":24959,"SuggestionType":1,"Location":null,"SubcategoryId":43,"Highlight":[{"Begin":12,"End":14}]},{"Text":"нарисовать шарж","SuggestionId":6961,"SuggestionType":1,"Location":null,"SubcategoryId":150,"Highlight":[{"Begin":11,"End":13}]},{"Text":"сделать шатуш","SuggestionId":29645,"SuggestionType":1,"Location":null,"SubcategoryId":43,"Highlight":[{"Begin":8,"End":10}]},{"Text":"надуть шарики гелием","SuggestionId":16884,"SuggestionType":1,"Location":null,"SubcategoryId":55,"Highlight":[{"Begin":7,"End":9}]},{"Text":"связать шапку","SuggestionId":3610,"SuggestionType":1,"Location":null,"SubcategoryId":121,"Highlight":[{"Begin":8,"End":10}]},{"Text":"сделать окрашивание шатуш","SuggestionId":19927,"SuggestionType":1,"Location":null,"SubcategoryId":43,"Highlight":[{"Begin":20,"End":22}]}],"IsSuccess":true,"Code":0,"Message":"","Timestamp":1598810532784.58}